insect/__init__.py
insect/__main__.py
insect/cli.py
insect/core.py
insect/dashboard.py
insect/finding.py
insect/analysis/__init__.py
insect/analysis/additional_rules.py
insect/analysis/binary_analyzer.py
insect/analysis/browser_theft_analyzer.py
insect/analysis/container_analyzer.py
insect/analysis/crypto_wallet_analyzer.py
insect/analysis/dependency_manager.py
insect/analysis/javascript_static_analyzer.py
insect/analysis/llm_exploitation_analyzer.py
insect/analysis/malicious_character_analyzer.py
insect/analysis/metadata_analyzer.py
insect/analysis/python_ast_visitor.py
insect/analysis/python_static_analyzer.py
insect/analysis/secret_analyzer.py
insect/analysis/static_analyzer.py
insect/analysis/static_analyzer_rules.py
insect/analysis/static_analyzer_utils.py
insect/analysis/vulnerability_analyzer.py
insect/analysis/config/__init__.py
insect/analysis/config/config_analyzer.py
insect/analysis/shell/__init__.py
insect/analysis/shell/analyzer.py
insect/config/__init__.py
insect/config/handler.py
insect/reporting/__init__.py
insect/reporting/dashboard_html_formatter.py
insect/reporting/formatters.py
insect/reporting/html_formatter.py
insect/reporting/json_formatter.py
insect/reporting/text_formatter.py
insect/utils/__init__.py
insect/utils/cache_utils.py
insect/utils/docker_utils.py
insect/utils/file_utils.py
insect/utils/hash_utils.py
insect/utils/progress_utils.py
insect-0.1.9.dist-info/licenses/LICENSE
insect-0.1.9.dist-info/METADATA
insect-0.1.9.dist-info/WHEEL
insect-0.1.9.dist-info/entry_points.txt
insect-0.1.9.dist-info/top_level.txt
insect-0.1.9.dist-info/RECORD
