Metadata-Version: 2.4
Name: insect
Version: 0.1.9
Summary: Security-focused command line tool to scan Git repositories for potentially malicious code patterns
Author-email: Somasundaram Sekar <somasundaram@outlook.com>
License: MIT
Project-URL: Homepage, https://github.com/somasays/insect
Project-URL: Repository, https://github.com/somasays/insect
Project-URL: Documentation, https://github.com/somasays/insect#readme
Keywords: security,static-analysis,git,vulnerability-scanner,malware-detection
Classifier: Development Status :: 4 - Beta
Classifier: Intended Audience :: Developers
Classifier: License :: OSI Approved :: MIT License
Classifier: Programming Language :: Python :: 3
Classifier: Programming Language :: Python :: 3.13
Requires-Python: >=3.13
License-File: LICENSE
Requires-Dist: rich>=12.0.0
Requires-Dist: gitpython
Requires-Dist: yara-python
Requires-Dist: toml
Requires-Dist: jinja2
Requires-Dist: click>=8.0.0
Requires-Dist: requests>=2.25.0
Requires-Dist: packaging>=21.0
Requires-Dist: pyyaml>=6.0
Provides-Extra: dev
Requires-Dist: pytest>=7.0.0; extra == "dev"
Requires-Dist: pytest-cov>=4.0.0; extra == "dev"
Requires-Dist: black>=23.0.0; extra == "dev"
Requires-Dist: isort>=5.0.0; extra == "dev"
Requires-Dist: mypy>=1.0.0; extra == "dev"
Requires-Dist: ruff>=0.0.230; extra == "dev"
Requires-Dist: pre-commit>=3.0.0; extra == "dev"
Requires-Dist: flake8; extra == "dev"
Requires-Dist: twine; extra == "dev"
Requires-Dist: build; extra == "dev"
Requires-Dist: pytest-mock; extra == "dev"
Dynamic: license-file
